cryptonit_bot/Instructions.txt
cryptonit_bot/__init__.py
cryptonit_bot/bot.py
cryptonitbot-1.0.6.dist-info/LICENSE
cryptonitbot-1.0.6.dist-info/METADATA
cryptonitbot-1.0.6.dist-info/WHEEL
cryptonitbot-1.0.6.dist-info/entry_points.txt
cryptonitbot-1.0.6.dist-info/top_level.txt
cryptonitbot-1.0.6.dist-info/RECORD
