Metadata-Version: 2.1
Name: cryptonitbot
Version: 1.0.6
Summary: A bot for encryption and decryption using Telegram
Home-page: https://github.com/ruslanlap/Cryptonit-BOT
Author: ruslanlap
Author-email: your-email@example.com
Classifier: Programming Language :: Python :: 3
Classifier: License :: OSI Approved :: MIT License
Classifier: Operating System :: OS Independent
Requires-Python: >=3.6
License-File: LICENSE
Requires-Dist: cryptography
Requires-Dist: pyTelegramBotAPI
